{
  "SalesVisionCustomersData" : {
    "_id" : "wm-SalesVisionCustomersData-wm.LiveVariable-1603460508162",
    "name" : "SalesVisionCustomersData",
    "owner" : "Page",
    "category" : "wm.LiveVariable",
    "dataBinding" : [ ],
    "operation" : "read",
    "dataSet" : [ ],
    "type" : "Customers",
    "isList" : true,
    "saveInPhonegap" : false,
    "maxResults" : 20,
    "designMaxResults" : 10,
    "inFlightBehavior" : "executeLast",
    "startUpdate" : true,
    "autoUpdate" : true,
    "transformationRequired" : false,
    "liveSource" : "SalesVision",
    "ignoreCase" : true,
    "matchMode" : "startignorecase",
    "orderBy" : "id asc",
    "propertiesMap" : {
      "columns" : [ {
        "fieldName" : "states",
        "type" : "integer",
        "fullyQualifiedType" : "integer",
        "columnName" : "STATE_ID",
        "isPrimaryKey" : false,
        "notNull" : false,
        "length" : 0,
        "precision" : 10,
        "generator" : "assigned",
        "isRelated" : true,
        "relatedTableName" : "STATES",
        "relatedEntityName" : "States",
        "relatedColumnName" : "stateId",
        "relatedFieldName" : "states.id",
        "isList" : false,
        "targetTable" : "STATES",
        "scale" : 0,
        "columns" : [ {
          "fieldName" : "id",
          "type" : "integer",
          "fullyQualifiedType" : "integer",
          "columnName" : "ID",
          "isPrimaryKey" : true,
          "notNull" : true,
          "length" : 0,
          "precision" : 10,
          "generator" : "identity",
          "isRelated" : false,
          "scale" : 0
        }, {
          "fieldName" : "name",
          "type" : "string",
          "fullyQualifiedType" : "string",
          "columnName" : "NAME",
          "isPrimaryKey" : false,
          "notNull" : true,
          "length" : 40,
          "precision" : 0,
          "generator" : "assigned",
          "isRelated" : false,
          "scale" : 0
        }, {
          "fieldName" : "abbrev",
          "type" : "string",
          "fullyQualifiedType" : "string",
          "columnName" : "ABBREV",
          "isPrimaryKey" : false,
          "notNull" : true,
          "length" : 2,
          "precision" : 0,
          "generator" : "assigned",
          "isRelated" : false,
          "scale" : 0
        } ]
      }, {
        "fieldName" : "id",
        "type" : "integer",
        "fullyQualifiedType" : "integer",
        "columnName" : "ID",
        "isPrimaryKey" : true,
        "notNull" : true,
        "length" : 0,
        "precision" : 10,
        "generator" : "identity",
        "isRelated" : false,
        "scale" : 0
      }, {
        "fieldName" : "name",
        "type" : "string",
        "fullyQualifiedType" : "string",
        "columnName" : "NAME",
        "isPrimaryKey" : false,
        "notNull" : true,
        "length" : 32,
        "precision" : 0,
        "generator" : "assigned",
        "isRelated" : false,
        "scale" : 0
      }, {
        "fieldName" : "company",
        "type" : "string",
        "fullyQualifiedType" : "string",
        "columnName" : "COMPANY",
        "isPrimaryKey" : false,
        "notNull" : false,
        "length" : 255,
        "precision" : 0,
        "generator" : "assigned",
        "isRelated" : false,
        "defaultValue" : "",
        "scale" : 0
      } ],
      "entityName" : "Customers",
      "fullyQualifiedName" : "com.salesvision.salesvision.Customers",
      "tableType" : "TABLE",
      "primaryFields" : [ "id" ]
    },
    "isDefault" : true,
    "bindCount" : 1,
    "tableName" : "CUSTOMERS",
    "tableType" : "TABLE",
    "properties" : [ "states" ],
    "relatedTables" : [ {
      "columnName" : "states",
      "relationName" : "states",
      "type" : "States",
      "watchOn" : "SalesVisionStatesData",
      "package" : "com.salesvision.salesvision.Customers"
    } ],
    "filterExpressions" : { },
    "package" : "com.salesvision.salesvision.Customers"
  }
}
